pangeo_sphinx_book_theme/__init__.py
pangeo_sphinx_book_theme/_version.py
pangeo_sphinx_book_theme/theme.conf
pangeo_sphinx_book_theme/static/custom.css
pangeo_sphinx_book_theme/static/pangeo-logo.png
pangeo_sphinx_book_theme/static/panton.black-caps.otf
pangeo_sphinx_book_theme/static/panton.light-caps.otf
pangeo_sphinx_book_theme-0.2.dist-info/LICENSE
pangeo_sphinx_book_theme-0.2.dist-info/METADATA
pangeo_sphinx_book_theme-0.2.dist-info/WHEEL
pangeo_sphinx_book_theme-0.2.dist-info/entry_points.txt
pangeo_sphinx_book_theme-0.2.dist-info/top_level.txt
pangeo_sphinx_book_theme-0.2.dist-info/RECORD
