Metadata-Version: 2.1
Name: pangeo-sphinx-book-theme
Version: 0.2
Summary: Pangeo's customized version of the Sphinx Book Theme.
Home-page: https://github.com/pangeo-forge/pangeo-sphinx-book-theme/
Author: Ryan Abernathey
Author-email: rpa@ldeo.columbia.edu
Maintainer: Charles Stern
Maintainer-email: cstern@ldeo.columbia.edu
License: MIT
Classifier: Framework :: Sphinx
Classifier: Framework :: Sphinx :: Theme
Classifier: Development Status :: 5 - Production/Stable
Classifier: License :: OSI Approved :: MIT License
Classifier: Environment :: Console
Classifier: Environment :: Web Environment
Classifier: Intended Audience :: Developers
Classifier: Programming Language :: Python :: 2.7
Classifier: Programming Language :: Python :: 3
Classifier: Programming Language :: Python :: 3.3
Classifier: Programming Language :: Python :: 3.4
Classifier: Programming Language :: Python :: 3.5
Classifier: Programming Language :: Python :: 3.6
Classifier: Operating System :: OS Independent
Classifier: Topic :: Documentation
Classifier: Topic :: Software Development :: Documentation
License-File: LICENSE
Requires-Dist: sphinx
Requires-Dist: sphinx-book-theme
